{"type":"PR","pr":{"number":1,"head":"d1eaef2d60e2584fb864e175994f40a927ac2584"},"user":"Carl Tanner","status":"draft","branch":"cms/blog/2020-01-13-good-men","collection":"blog","commitMessage":"Create Blog “2020-01-13-good-men”","title":"good men","description":"No Description!","objects":{"entry":{"path":"content/blog/2020-01-13-good-men.json","sha":"c0cd2d57e03c45b6e2b113af7e29f6e1796d1018"},"files":[{"path":"static/images/uploads/Screen Shot 2020-01-07 at 6.30.10 PM.png","sha":"3a0a008b4d0ca81316583493f651ff348d27ec3c"}]},"timeStamp":"2020-01-13T00:27:04.866Z","version":"1"}